LICENSE
pyproject.toml
setup.cfg
setup.py
src/MicaelJarniac_cookiecutter_python_project_test.egg-info/PKG-INFO
src/MicaelJarniac_cookiecutter_python_project_test.egg-info/SOURCES.txt
src/MicaelJarniac_cookiecutter_python_project_test.egg-info/dependency_links.txt
src/MicaelJarniac_cookiecutter_python_project_test.egg-info/not-zip-safe
src/MicaelJarniac_cookiecutter_python_project_test.egg-info/top_level.txt
src/cookiecutter_python_project_test/__init__.py
src/cookiecutter_python_project_test/_cookiecutter_python_project_test.py
src/cookiecutter_python_project_test/py.typed