Metadata-Version: 2.1
Name: MicaelJarniac-cookiecutter-python-project-test
Version: 0.1.0
Summary: A simple Python project template.
Home-page: https://github.com/MicaelJarniac/cookiecutter-python-project-test
Author: Micael Jarniac
Author-email: micael@jarniac.dev
License: MIT
Project-URL: Changelog, https://github.com/MicaelJarniac/cookiecutter-python-project-test/blob/main/docs/CHANGELOG.md
Project-URL: Documentation, https://cookiecutter_python_project_test.readthedocs.io
Project-URL: Repository, https://github.com/MicaelJarniac/cookiecutter-python-project-test
Project-URL: Bug Tracker, https://github.com/MicaelJarniac/cookiecutter-python-project-test/issues
Platform: UNKNOWN
Classifier: Development Status :: 1 - Planning
Classifier: License :: OSI Approved :: MIT License
Classifier: Natural Language :: English
Classifier: Operating System :: OS Independent
Classifier: Programming Language :: Python :: 3
Classifier: Programming Language :: Python :: 3 :: Only
Classifier: Programming Language :: Python :: 3.7
Classifier: Programming Language :: Python :: 3.8
Classifier: Programming Language :: Python :: 3.9
Classifier: Programming Language :: Python :: 3.10
Classifier: Typing :: Typed
Requires-Python: >=3.7
License-File: LICENSE
